cjy_wfy5/__init__.py
cjy_wfy5/background.jpg
cjy_wfy5/crash.wav
cjy_wfy5/main.py
cjy_wfy5/racecar.jpg
cjy_wfy5/racestart.wav
cjy_wfy5/tiantiande.wav
cjy_wfy5/photos/1.jpg
cjy_wfy5/photos/10.jpg
cjy_wfy5/photos/11.jpg
cjy_wfy5/photos/12.jpg
cjy_wfy5/photos/13.jpg
cjy_wfy5/photos/14.jpg
cjy_wfy5/photos/15.jpg
cjy_wfy5/photos/2.jpg
cjy_wfy5/photos/3.jpg
cjy_wfy5/photos/4.jpg
cjy_wfy5/photos/5.jpg
cjy_wfy5/photos/6.jpg
cjy_wfy5/photos/7.jpg
cjy_wfy5/photos/70.jpg
cjy_wfy5/photos/8.jpg
cjy_wfy5/photos/9.jpg
cjy_wfy5-0.0.1.dist-info/LICENSE
cjy_wfy5-0.0.1.dist-info/METADATA
cjy_wfy5-0.0.1.dist-info/WHEEL
cjy_wfy5-0.0.1.dist-info/top_level.txt
cjy_wfy5-0.0.1.dist-info/RECORD
